{
  "god_of_blood" : {
    "color" : "red",
    "image" : "img_god_of_blood",
    "name" : "lbl_god_of_blood",
    "description": "lbl_god_of_blood_description",
    "damage": 20,
    "health": 0,
    "goldProduction": 0,
    "peopleProduction": 0,
    "manaProduction": 0,
    "bid": 0,
    "power": 100000
  },
  "god_of_death" : {
    "color" : "purple",
    "image" : "img_god_of_death",
    "name" : "lbl_god_of_death",
    "description": "lbl_god_of_death_description",
    "damage": 0,
    "health": 0,
    "goldProduction": 0,
    "peopleProduction": 20000,
    "manaProduction": 0,
    "bid": 0,
    "power": 100000
  },
  "god_of_life" : {
    "color" : "green",
    "image" : "img_god_of_life",
    "name" : "lbl_god_of_life",
    "description": "lbl_god_of_life_description",
    "damage": 0,
    "health": 20,
    "goldProduction": 0,
    "peopleProduction": 0,
    "manaProduction": 0,
    "bid": 0,
    "power": 100000
  },
  "god_of_light" : {
    "color" : "white",
    "image" : "img_god_of_light",
    "name" : "lbl_god_of_light",
    "description": "lbl_god_of_light_description",
    "damage": 0,
    "health": 0,
    "goldProduction": 30000,
    "peopleProduction": 0,
    "manaProduction": 0,
    "bid": 0,
    "power": 100000
  },
  "god_of_magic" : {
    "color" : "blue",
    "image" : "img_god_of_magic",
    "name" : "lbl_god_of_magic",
    "description": "lbl_god_of_magic_description",
    "damage": 0,
    "health": 0,
    "goldProduction": 0,
    "peopleProduction": 0,
    "manaProduction": 10000,
    "bid": 0,
    "power": 100000
  }
}
